upnp_port_forward/__init__.py
upnp_port_forward/client.py
upnp_port_forward/exceptions.py
upnp_port_forward/py.typed
upnp_port_forward/typing.py
upnp_port_forward-0.1.2.dist-info/LICENSE
upnp_port_forward-0.1.2.dist-info/METADATA
upnp_port_forward-0.1.2.dist-info/WHEEL
upnp_port_forward-0.1.2.dist-info/top_level.txt
upnp_port_forward-0.1.2.dist-info/RECORD
